mcp_simulator/__init__.py
mcp_simulator/__main__.py
mcp_simulator/server.py
mcp_simulator-0.1.2.dist-info/METADATA
mcp_simulator-0.1.2.dist-info/WHEEL
mcp_simulator-0.1.2.dist-info/entry_points.txt
mcp_simulator-0.1.2.dist-info/RECORD
