Metadata-Version: 2.4
Name: mcp_simulator
Version: 0.1.2
Summary: MCP server for lineup and projection simulation tools
Requires-Python: >=3.10
Requires-Dist: mcp>=1.2.0
Requires-Dist: pandas
